hypergbm/__init__.py
hypergbm/_version.py
hypergbm/cfg.py
hypergbm/estimators.py
hypergbm/experiment.py
hypergbm/gpu_job.py
hypergbm/hyper_gbm.py
hypergbm/job.py
hypergbm/objectives.py
hypergbm/search_space.py
hypergbm/cuml/__init__.py
hypergbm/cuml/_estimators.py
hypergbm/cuml/_hyper_gbm.py
hypergbm/cuml/_ops.py
hypergbm/cuml/_search_space.py
hypergbm/dask/__init__.py
hypergbm/dask/_estimators.py
hypergbm/dask/dask_ops.py
hypergbm/dask/dask_transformers.py
hypergbm/dask/search_space.py
hypergbm/examples/00.get-doc.ipynb
hypergbm/examples/01.quick-start.ipynb
hypergbm/examples/02.basic-setting.ipynb
hypergbm/examples/11.feature_selection.ipynb
hypergbm/examples/12.collinearity_detection.ipynb
hypergbm/examples/13.drift_detection.ipynb
hypergbm/examples/14.feature_generation_datetime.ipynb
hypergbm/examples/15.feature_generation_latlong_text.ipynb
hypergbm/examples/17.feature_reselection.ipynb
hypergbm/examples/18.pseudo_labeling.ipynb
hypergbm/examples/21.classbalance.ipynb
hypergbm/examples/31.search_space.ipynb
hypergbm/examples/32.customize_estimator.ipynb
hypergbm/examples/33.multiple_objectives.ipynb
hypergbm/examples/51.HyperGBM.ipynb
hypergbm/examples/61.NSGAII_example.ipynb
hypergbm/examples/62.RNSGAII_example.ipynb
hypergbm/examples/63.MOEAD_example.ipynb
hypergbm/examples/66.Objectives_example.ipynb
hypergbm/examples/71.hypergbm_shap.ipynb
hypergbm/examples/72.hypegbm_experiment_notebook_visualization.ipynb
hypergbm/examples/73.hypergbm_shap_explainer.ipynb
hypergbm/examples/74.hypergbm_experiment_explainer.ipynb
hypergbm/examples/C01.quick-start-with-RAPIDS(cuDF_cuML).ipynb
hypergbm/examples/datasets/Bank/test.csv.gz
hypergbm/examples/datasets/Bank/train.csv.gz
hypergbm/examples/datasets/Magic/test.csv.gz
hypergbm/examples/datasets/Magic/train.csv.gz
hypergbm/examples/datasets/Metro_Interstate_Traffic_Volume/data.csv.gz
hypergbm/examples/datasets/Spambase/test.csv.gz
hypergbm/examples/datasets/Spambase/train.csv.gz
hypergbm-0.3.2.dist-info/LICENSE
hypergbm-0.3.2.dist-info/METADATA
hypergbm-0.3.2.dist-info/WHEEL
hypergbm-0.3.2.dist-info/entry_points.txt
hypergbm-0.3.2.dist-info/top_level.txt
hypergbm-0.3.2.dist-info/RECORD
