Metadata-Version: 2.1
Name: hypergbm
Version: 0.3.2
Summary: A full pipeline AutoML tool integrated various GBM models
Home-page: https://github.com/DataCanvasIO/HyperGBM
Author: DataCanvas Community
Author-email: yangjian@zetyun.com
License: Apache License 2.0
Classifier: Operating System :: OS Independent
Classifier: Intended Audience :: Developers
Classifier: Intended Audience :: Education
Classifier: Intended Audience :: Science/Research
Classifier: Programming Language :: Python
Classifier: Programming Language :: Python :: 3.6
Classifier: Programming Language :: Python :: 3.7
Classifier: Programming Language :: Python :: 3.8
Classifier: Programming Language :: Python :: 3.9
Classifier: Programming Language :: Python :: 3.10
Classifier: Topic :: Scientific/Engineering
Classifier: Topic :: Scientific/Engineering :: Artificial Intelligence
Classifier: Topic :: Software Development
Classifier: Topic :: Software Development :: Libraries
Classifier: Topic :: Software Development :: Libraries :: Python Modules
Requires-Python: >=3.6
License-File: LICENSE
Requires-Dist: hypernets <0.4.0,>=0.3.1
Requires-Dist: scikit-learn >=0.22.1
Requires-Dist: fsspec >=0.8.0
Requires-Dist: lightgbm >=3.2.0
Requires-Dist: xgboost >=1.3.0
Requires-Dist: catboost >=0.26
Requires-Dist: imbalanced-learn >=0.7.0
Requires-Dist: tqdm
Provides-Extra: all
Requires-Dist: dask !=2023.2.1,!=2023.3.*,!=2023.4.*,!=2023.5.* ; extra == 'all'
Requires-Dist: dask-ml ; extra == 'all'
Requires-Dist: distributed !=2023.2.1,!=2023.3.*,!=2023.4.*,!=2023.5.* ; extra == 'all'
Requires-Dist: featuretools >=0.23.0 ; extra == 'all'
Requires-Dist: ipywidgets ; extra == 'all'
Requires-Dist: jieba ; extra == 'all'
Requires-Dist: jupyterlab ; extra == 'all'
Requires-Dist: jupyterlab-widgets ; extra == 'all'
Requires-Dist: matplotlib <3.6 ; extra == 'all'
Requires-Dist: pytest ; extra == 'all'
Requires-Dist: shap ; extra == 'all'
Provides-Extra: board
Requires-Dist: ipywidgets ; extra == 'board'
Provides-Extra: dask
Requires-Dist: dask !=2023.2.1,!=2023.3.*,!=2023.4.*,!=2023.5.* ; extra == 'dask'
Requires-Dist: distributed !=2023.2.1,!=2023.3.*,!=2023.4.*,!=2023.5.* ; extra == 'dask'
Requires-Dist: dask-ml ; extra == 'dask'
Provides-Extra: fg
Requires-Dist: featuretools >=0.23.0 ; extra == 'fg'
Provides-Extra: notebook
Requires-Dist: jupyterlab ; extra == 'notebook'
Requires-Dist: ipywidgets ; extra == 'notebook'
Requires-Dist: jupyterlab-widgets ; extra == 'notebook'
Provides-Extra: shap
Requires-Dist: shap ; extra == 'shap'
Requires-Dist: matplotlib <3.6 ; extra == 'shap'
Provides-Extra: tests
Requires-Dist: pytest ; extra == 'tests'
Provides-Extra: zhcn
Requires-Dist: jieba ; extra == 'zhcn'
